psyfar_downloader/__init__.py
psyfar_downloader/psyfar_downloader.py
psyfar_downloader-0.1.1.dist-info/LICENSE
psyfar_downloader-0.1.1.dist-info/METADATA
psyfar_downloader-0.1.1.dist-info/WHEEL
psyfar_downloader-0.1.1.dist-info/entry_points.txt
psyfar_downloader-0.1.1.dist-info/top_level.txt
psyfar_downloader-0.1.1.dist-info/RECORD
