Metadata-Version: 2.1
Name: psyfar-downloader
Version: 0.1.1
Summary: Download Psyfar and convert to EPUB
Home-page: https://gitlab.com/fvdbeek/psyfar-downloader
Author: Folkert van der Beek
Author-email: folkertvanderbeek@gmail.com
License: MIT License
Project-URL: Bug Tracker, https://gitlab.com/fvdbeek/psyfar-downloader/-/issues
Keywords: Psyfar,download,epub
Classifier: Development Status :: 3 - Alpha
Classifier: License :: OSI Approved :: MIT License
Classifier: Operating System :: OS Independent
Classifier: Programming Language :: Python :: 3
Classifier: Programming Language :: Python :: 3.8
Classifier: Programming Language :: Python :: 3.9
Classifier: Topic :: Utilities
Requires-Python: >=3.8
License-File: LICENSE
Requires-Dist: appdirs
Requires-Dist: beautifulsoup4
Requires-Dist: EbookLib
Requires-Dist: lxml
Requires-Dist: requests
Requires-Dist: sanitize-filename
Requires-Dist: tabulate
Requires-Dist: w3lib
